azureml/__init__.py
azureml/contrib/__init__.py
azureml/contrib/opendatasets/__init__.py
azureml/contrib/opendatasets/_boston_reported_crime.py
azureml/contrib/opendatasets/_boston_reported_crime_blob_info.py
azureml/contrib/opendatasets/_boston_safety.py
azureml/contrib/opendatasets/_boston_safety_blob_info.py
azureml/contrib/opendatasets/_chicago_reported_crime.py
azureml/contrib/opendatasets/_chicago_reported_crime_blob_info.py
azureml/contrib/opendatasets/_chicago_safety.py
azureml/contrib/opendatasets/_chicago_safety_blob_info.py
azureml/contrib/opendatasets/_noaa_gfs_weather.py
azureml/contrib/opendatasets/_noaa_gfs_weather_blob_info.py
azureml/contrib/opendatasets/_noaa_isd_weather.py
azureml/contrib/opendatasets/_noaa_isd_weather_blob_info.py
azureml/contrib/opendatasets/_nyc_reported_crime.py
azureml/contrib/opendatasets/_nyc_reported_crime_blob_info.py
azureml/contrib/opendatasets/_nyc_safety.py
azureml/contrib/opendatasets/_nyc_safety_blob_info.py
azureml/contrib/opendatasets/_nyc_tlc_fhv.py
azureml/contrib/opendatasets/_nyc_tlc_fhv_blob_info.py
azureml/contrib/opendatasets/_nyc_tlc_green.py
azureml/contrib/opendatasets/_nyc_tlc_green_blob_info.py
azureml/contrib/opendatasets/_nyc_tlc_yellow.py
azureml/contrib/opendatasets/_nyc_tlc_yellow_blob_info.py
azureml/contrib/opendatasets/_public_holidays.py
azureml/contrib/opendatasets/_public_holidays_blob_info.py
azureml/contrib/opendatasets/_sanfrancisco_reported_crime.py
azureml/contrib/opendatasets/_sanfrancisco_reported_crime_blob_info.py
azureml/contrib/opendatasets/_sanfrancisco_safety.py
azureml/contrib/opendatasets/_sanfrancisco_safety_blob_info.py
azureml/contrib/opendatasets/_seattle_reported_crime.py
azureml/contrib/opendatasets/_seattle_reported_crime_blob_info.py
azureml/contrib/opendatasets/_seattle_safety.py
azureml/contrib/opendatasets/_seattle_safety_blob_info.py
azureml/contrib/opendatasets/city_reported_crime.py
azureml/contrib/opendatasets/city_safety.py
azureml_contrib_opendatasets-1.0.45.dist-info/DESCRIPTION.rst
azureml_contrib_opendatasets-1.0.45.dist-info/LICENSE.txt
azureml_contrib_opendatasets-1.0.45.dist-info/METADATA
azureml_contrib_opendatasets-1.0.45.dist-info/RECORD
azureml_contrib_opendatasets-1.0.45.dist-info/WHEEL
azureml_contrib_opendatasets-1.0.45.dist-info/metadata.json
azureml_contrib_opendatasets-1.0.45.dist-info/top_level.txt
