Metadata-Version: 2.0
Name: azureml-contrib-opendatasets
Version: 1.0.45
Summary: Azure Machine Learning Open Datasets
Home-page: https://docs.microsoft.com/en-us/azure/machine-learning/service/
Author: Microsoft Corp
License: Proprietary https://aka.ms/azureml-preview-sdk-license 
Platform: UNKNOWN
Requires-Dist: azureml-telemetry (==1.0.45.*)
Requires-Dist: azure-storage-blob
Requires-Dist: multimethods
Requires-Dist: numpy
Requires-Dist: pandas (>=0.23.0)
Requires-Dist: pyarrow
Requires-Dist: pyspark
